IamDJCore/__init__.py
IamDJCore/main.py
iamdjcore-0.2.1.dist-info/METADATA
iamdjcore-0.2.1.dist-info/WHEEL
iamdjcore-0.2.1.dist-info/licenses/LICENSE
iamdjcore-0.2.1.dist-info/RECORD
