Metadata-Version: 2.3
Name: IamDJCore
Version: 0.2.1
Summary: Only package you will every need ;).
Project-URL: Homepage, https://github.com/pypa/sampleproject
Project-URL: Issues, https://github.com/pypa/sampleproject/issues
Author-email: DJ_Ryu_Jin_Sama <dhananjay2k3148@gmail.com>
Classifier: License :: OSI Approved :: MIT License
Classifier: Operating System :: OS Independent
Classifier: Programming Language :: Python :: 3
Requires-Python: >=3.8
